beagle/__init__.py
beagle/config.py
beagle/constants.py
beagle/backends/__init__.py
beagle/backends/base_backend.py
beagle/backends/dgraph.py
beagle/backends/graphistry.py
beagle/backends/neo4j.py
beagle/backends/networkx.py
beagle/common/__init__.py
beagle/common/logging.py
beagle/config_templates/beagle_default.cfg
beagle/datasources/__init__.py
beagle/datasources/base_datasource.py
beagle/datasources/cuckoo_report.py
beagle/datasources/fireeye_ax_report.py
beagle/datasources/hx_triage.py
beagle/datasources/procmon_csv.py
beagle/datasources/sysmon_evtx.py
beagle/datasources/win_evtx.py
beagle/datasources/memory/__init__.py
beagle/datasources/memory/windows_rekall.py
beagle/datasources/virustotal/__init__.py
beagle/datasources/virustotal/generic_vt_sandbox.py
beagle/datasources/virustotal/generic_vt_sandbox_api.py
beagle/nodes/__init__.py
beagle/nodes/alert.py
beagle/nodes/domain.py
beagle/nodes/edge.py
beagle/nodes/file.py
beagle/nodes/ip_address.py
beagle/nodes/node.py
beagle/nodes/process.py
beagle/nodes/registry.py
beagle/transformers/__init__.py
beagle/transformers/base_transformer.py
beagle/transformers/evtx_transformer.py
beagle/transformers/fireeye_ax_transformer.py
beagle/transformers/fireeye_hx_transformer.py
beagle/transformers/generic_transformer.py
beagle/transformers/procmon_transformer.py
beagle/transformers/sysmon_transformer.py
beagle/web/__init__.py
beagle/web/server.py
beagle/web/wsgi.py
beagle/web/api/__init__.py
beagle/web/api/models.py
beagle/web/api/views.py
pybeagle-1.0.5.dist-info/LICENSE
pybeagle-1.0.5.dist-info/METADATA
pybeagle-1.0.5.dist-info/WHEEL
pybeagle-1.0.5.dist-info/top_level.txt
pybeagle-1.0.5.dist-info/RECORD
