Metadata-Version: 2.1
Name: pybeagle
Version: 1.0.5
Summary: Beagle is an incident response and digital forensics tool which transforms data sources and logs into graphs
Home-page: https://github.com/yampelo/beagle
Author: yampelo
License: MIT
Platform: UNKNOWN
Classifier: License :: OSI Approved :: MIT License
Classifier: Programming Language :: Python
Classifier: Programming Language :: Python :: 3
Classifier: Programming Language :: Python :: 3.6
Classifier: Programming Language :: Python :: 3.7
Classifier: Topic :: Software Development :: Libraries
Classifier: Topic :: Security
Classifier: Development Status :: 5 - Production/Stable
Classifier: Environment :: Web Environment
Classifier: Operating System :: OS Independent
Requires-Python: >=3.6.0
Requires-Dist: ansimarkup (==1.4.0)
Requires-Dist: atomicwrites (==1.3.0)
Requires-Dist: attrs (==19.1.0)
Requires-Dist: better-exceptions-fork (==0.2.1.post6)
Requires-Dist: certifi (==2019.3.9)
Requires-Dist: chardet (==3.0.4)
Requires-Dist: click (==7.0)
Requires-Dist: colorama (==0.4.1)
Requires-Dist: coverage (==5.0a4)
Requires-Dist: decorator (==4.4.0)
Requires-Dist: flask-sqlalchemy (==2.3.2)
Requires-Dist: flask (==1.0.2)
Requires-Dist: future (==0.16.0)
Requires-Dist: graphistry[networkx] (==0.9.63)
Requires-Dist: grpcio (==1.20.0rc3)
Requires-Dist: gunicorn (==19.9.0)
Requires-Dist: hexdump (==3.3)
Requires-Dist: idna (==2.8)
Requires-Dist: itsdangerous (==1.1.0)
Requires-Dist: jinja2 (==2.10.1)
Requires-Dist: loguru (==0.2.5)
Requires-Dist: lxml (==4.3.3)
Requires-Dist: markupsafe (==1.1.1)
Requires-Dist: neo4j (==1.7.2)
Requires-Dist: neobolt (==1.7.4)
Requires-Dist: neotime (==1.7.4)
Requires-Dist: networkx (==2.3rc3)
Requires-Dist: numpy (==1.16.2)
Requires-Dist: pandas (==0.24.2)
Requires-Dist: pluggy (==0.9.0)
Requires-Dist: protobuf (==3.6.1)
Requires-Dist: py (==1.8.0)
Requires-Dist: pydgraph (==1.0.3)
Requires-Dist: pygments (==2.3.1)
Requires-Dist: pytest-cov (==2.6.1)
Requires-Dist: pytest (==4.4.0)
Requires-Dist: python-dateutil (==2.8.0)
Requires-Dist: python-evtx (==0.6.1)
Requires-Dist: pytz (==2018.9)
Requires-Dist: requests (==2.21.0)
Requires-Dist: six (==1.12.0)
Requires-Dist: sqlalchemy (==1.3.2)
Requires-Dist: urllib3 (==1.24.1)
Requires-Dist: werkzeug (==0.15.2)
Requires-Dist: more-itertools (==7.0.0) ; python_version > "2.7"
Provides-Extra: rekall
Requires-Dist: rekall (==1.7.2rc1) ; extra == 'rekall'
